waylay/services/data/models/__init__.py
waylay/services/data/models/aggregate.py
waylay/services/data/models/delete_messages200_response.py
waylay/services/data/models/delete_series_from_parameter.py
waylay/services/data/models/error_response.py
waylay/services/data/models/event.py
waylay/services/data/models/event_timestamp.py
waylay/services/data/models/get_datapoints_for_metric_raw200_response.py
waylay/services/data/models/get_datapoints_for_metric_raw200_response_links.py
waylay/services/data/models/get_metric_series_from_parameter.py
waylay/services/data/models/get_series200_response_inner.py
waylay/services/data/models/get_series200_response_inner_latest.py
waylay/services/data/models/grouping.py
waylay/services/data/models/grouping_any_of.py
waylay/services/data/models/hal_link.py
waylay/services/data/models/latest_measurement.py
waylay/services/data/models/measurements.py
waylay/services/data/models/message_query.py
waylay/services/data/models/message_query_from.py
waylay/services/data/models/message_query_result.py
waylay/services/data/models/message_query_result_results_inner.py
waylay/services/data/models/message_query_until.py
waylay/services/data/models/message_query_window.py
waylay/services/data/models/multiple_series_query_request_inner.py
waylay/services/data/models/object.py
waylay/services/data/models/order.py
waylay/services/data/models/post_series_for_resource_request.py
waylay/services/data/models/post_series_request.py
waylay/services/data/models/publish_event_response.py
waylay/services/data/models/publish_event_response_content.py
waylay/services/data/models/publish_event_response_content_any_of.py
waylay/services/data/models/publish_resource_event_response.py
waylay/services/data/models/publish_resource_event_response_content.py
waylay/services/data/models/py.typed
waylay/services/data/models/query_time_series200_response.py
waylay/services/data/models/query_time_series_request.py
waylay/services/data/models/resource_event.py
waylay_sdk_data_types-2.18.0.20241025.dist-info/LICENSE.txt
waylay_sdk_data_types-2.18.0.20241025.dist-info/METADATA
waylay_sdk_data_types-2.18.0.20241025.dist-info/WHEEL
waylay_sdk_data_types-2.18.0.20241025.dist-info/top_level.txt
waylay_sdk_data_types-2.18.0.20241025.dist-info/RECORD
